datacollector/DataCollector.cpython-313-aarch64-linux-gnu.so
datacollector/DataCollectorConsole.cpython-313-aarch64-linux-gnu.so
datacollector/__init__.py
datacollector/log_config.cpython-313-aarch64-linux-gnu.so
datacollector/opc_thread.cpython-313-aarch64-linux-gnu.so
datacollector/pics/collector_icon.ico
taiji_datacollector-1.3.0.dist-info/METADATA
taiji_datacollector-1.3.0.dist-info/WHEEL
taiji_datacollector-1.3.0.dist-info/top_level.txt
taiji_datacollector-1.3.0.dist-info/RECORD
