Metadata-Version: 2.4
Name: taiji-datacollector
Version: 1.3.0
Summary: datacollector GUI tools for Tai-Ji Control
Author-email: Kangkang Zhang <kkzhang3@hotmail.com>
Requires-Python: >=3.12
Requires-Dist: PyQt5>=5.15
Requires-Dist: loguru
Requires-Dist: QtPy
Requires-Dist: tsdbpy>=0.3.3
Requires-Dist: pyidh
Requires-Dist: psycopg
Requires-Dist: psycopg-binary
Provides-Extra: dev
Requires-Dist: pytest; extra == "dev"
